{"id":"02ab195a1a5465180becdd7c108fe597","word":"Meeschterbréif","types":[{"type":"noun","lodKey":"MEESCHTERBREIF1","details":{"nounGender":"M","plural":"Meeschterbréiwer","audio":"meeschterbreif1.m4a"},"meanings":[{"examples":[{"example":"mat engem Meeschterbréif huet een d'Méiglechkeet, fir säin eegene Betrib ze grënnen a Leit auszebilden","usage":"ALLG"}],"synonyms":[],"translations":[{"language":"ALL","translation":"Meisterbrief","complement":"Ausbildungsgrad"},{"language":"FR","translation":"brevet de maîtrise","complement":"niveau de formation"},{"language":"PO"},{"language":"EN"}]},{"examples":[{"example":"d' Meeschterbréiwer ginn am Festsall iwwerreecht","usage":"ALLG"}],"synonyms":[],"translations":[{"language":"ALL","translation":"Meisterbrief","complement":"Dokument"},{"language":"FR","translation":"brevet de maîtrise","complement":"document"},{"language":"PO"},{"language":"EN"}]}]}]}