{"id":"405a348b4c1a6b966e4d865c43b304f0","word":"Kaffi","types":[{"type":"noun","lodKey":"KAFFI1","details":{"nounGender":"M","plural":"Kaffien","audio":"kaffi1.m4a"},"meanings":[{"examples":[{"example":"bei eis wiisst kee Kaffi","usage":"ALLG"}],"synonyms":[],"translations":[{"language":"ALL","translation":"Kaffee","complement":"Pflanze"},{"language":"FR","translation":"café","complement":"plante"},{"language":"PO","translation":"café","complement":"planta"},{"language":"EN"}]},{"examples":[{"example":"wann de Kaffi geréischtert gëtt, entfaalt sech den Aroma","usage":"ALLG"}],"synonyms":[],"translations":[{"language":"ALL","translation":"Kaffee","complement":"Bohnen"},{"language":"FR","translation":"café","complement":"graines"},{"language":"PO","translation":"café","complement":"sementes"},{"language":"EN"}]},{"examples":[{"example":"maach mer just e klenge Läffel Kaffi an d'Taass","usage":"ALLG"}],"synonyms":[],"translations":[{"language":"ALL","translation":"Kaffee","complement":"Pulver"},{"language":"FR","translation":"café","complement":"poudre"},{"language":"PO","translation":"café","complement":"pó"},{"language":"EN","translation":"coffee","complement":"powder"}]},{"examples":[{"example":"mir hunn eng Taass Kaffi gedronk","usage":"ALLG"}],"synonyms":[],"translations":[{"language":"ALL","translation":"Kaffee","complement":"Getränk"},{"language":"FR","translation":"café","complement":"boisson"},{"language":"PO","translation":"café","complement":"bebida"},{"language":"EN","translation":"coffee","complement":"drink"}]},{"examples":[{"example":"bestell eis nach zwee Kaffien !","usage":"ALLG"}],"synonyms":[],"translations":[{"language":"ALL","translation":"(Tasse) Kaffee"},{"language":"FR","translation":"(tasse de) café"},{"language":"PO","translation":"(chávena de) café"},{"language":"EN","translation":"(cup of) coffee"}]},{"examples":[{"example":"mueres beim Kaffi iessen ech dacks eng Hunnegschmier","usage":"ALLG"}],"synonyms":[],"translations":[{"language":"ALL","translation":"Frühstück"},{"language":"FR","translation":"petit-déjeuner"},{"language":"PO","translation":"pequeno-almoço"},{"language":"EN","translation":"breakfast"}]}]}]}