{"id":"49235dd60839eaae5f9fbe7f4303717b","word":"Jux","types":[{"type":"noun","lodKey":"JUX1","details":{"nounGender":"M","audio":"jux1.m4a"},"meanings":[{"examples":[{"example":"hien huet aus Jux seng Stëmm um Telefon verstallt","usage":"ALLG"}],"synonyms":[],"polyLex":"aus Jux","translations":[{"language":"ALL","translation":"aus Jux"},{"language":"FR","translation":"par plaisanterie"},{"language":"PO","translation":"por brincadeira"},{"language":"EN","translation":"for fun"}]},{"examples":[{"example":"méchs du de Jux mat mir?","usage":"ALLG"},{"example":"mat esou eeschte Saache mécht een de Jux net!","usage":"ALLG"}],"synonyms":[],"polyLex":"de Jux maache mat","translations":[{"language":"ALL","translation":"sich lustig machen über"},{"language":"FR","translation":"se moquer de"},{"language":"PO","translation":"gozar com"},{"language":"EN","translation":"to take the mickey out of"}]}]}]}