{"id":"4ce60fb5538c99aa9cef06a2b6e8c292","word":"Héichsprénger","types":[{"type":"noun","lodKey":"HEICHSPRENGER1","details":{"nounGender":"M","nounCategory":"SUBST","plural":"Héichsprénger","audio":"heichsprenger1.m4a"},"meanings":[{"examples":[{"example":"deen Héichsprénger huet schonn dräimol säin eegene Rekord gebrach","usage":"ALLG"}],"synonyms":[],"translations":[{"language":"ALL","translation":"Hochspringer"},{"language":"FR","translation":"sauteur en hauteur"},{"language":"PO","translation":"saltador em altura"},{"language":"EN","translation":"high jumper"}]}]}]}