{"id":"822a21254d4792faa3946578e3f49333","word":"Orthodontist","types":[{"type":"noun","lodKey":"ORTHODONTIST1","details":{"nounGender":"M","plural":"Orthodontisten","audio":"orthodontist1.m4a"},"meanings":[{"examples":[{"example":"wéinst enger markanter Feelstellung vu sengen Zänn geet eist Klengt elo bei en Orthodontist","usage":"ALLG"}],"synonyms":[],"translations":[{"language":"ALL","translation":"Kieferorthopäde"},{"language":"FR","translation":"orthodontiste"},{"language":"PO","translation":"ortodontista"},{"language":"EN","translation":"orthodontist"}]}]}]}