{"id":"9446a98ad14416153cc4d45ab8b531bf","word":"Performance","types":[{"type":"noun","lodKey":"PERFORMANCE1","details":{"nounGender":"F","plural":"Performancen","audio":"performance1.m4a"},"meanings":[{"examples":[{"example":"de Sportler huet haut eng fantastesch Performance bruecht","usage":"ALLG"},{"example":"fir zwanzeg Mann ze kachen ass eng schéi Performance !","usage":"ALLG"}],"synonyms":[],"translations":[{"language":"ALL","translation":"Leistung","complement":"(Ergebnis einer) Anstrengung"},{"language":"FR","translation":"performance"},{"language":"PO","translation":"performance"},{"language":"EN","translation":"performance"}]}]}]}