{"id":"ab99744be4f71df29f424c7a81906402","word":"Krauselkapp","types":[{"type":"noun","lodKey":"KRAUSELKAPP1","details":{"nounGender":"M","plural":"Krauselkäpp","audio":"krauselkapp1.m4a"},"meanings":[{"examples":[{"example":"meng kleng Schwëster huet e léiwe Krauselkapp","usage":"ALLG"}],"synonyms":[],"translations":[{"language":"ALL","translation":"Lockenkopf"},{"language":"FR","translation":"tête bouclée"},{"language":"PO","translation":"cabelo encaracolado"},{"language":"EN","translation":"head full of curls"}]}]}]}