{"id":"bc9de31edfef363ca6ee21e485a5512e","word":"futtilaachen","types":[{"type":"verb","lodKey":"FUTTILAACHEN1","details":{"auxiliaryVerb":"HUNN","pastParticiples":["futtigelaacht"],"verbCategory":"VRB","audio":"futtilaachen1.m4a"},"meanings":[{"examples":[{"example":"mat mengem Bop kann ee sech heiansdo futtilaachen","usage":"EGS"}],"synonyms":[],"reflexivePronoun":"PRONOM","employsImpersonal":"VRB-EMPL-IMPERS-IMPOSS","translations":[{"language":"ALL","translation":"sich kaputtlachen"},{"language":"FR","translation":"se tordre de rire"},{"language":"PO","translation":"partir-se a rir"},{"language":"EN","translation":"to kill oneself laughing"}]}]}]}