{"id":"bcf14a49d98ad22809be668b393cface","word":"Promoteur","types":[{"type":"noun","lodKey":"PROMOTEUR1","details":{"nounGender":"M","plural":"Promoteuren","audio":"promoteur1.m4a"},"meanings":[{"examples":[{"example":"e Promoteur huet dat ganzt Areal opkaaft, fir do eng Cité ze bauen","usage":"ALLG"}],"synonyms":[],"translations":[{"language":"ALL","translation":"Bauträger"},{"language":"FR","translation":"promoteur (immobilier)"},{"language":"PO","translation":"promotor imobiliário"},{"language":"EN","translation":"property developer"}]}]}]}