{"id":"c374774cb9609e06c540157c04e85f47","word":"Jury","types":[{"type":"noun","lodKey":"JURY1","details":{"nounGender":"MF","plural":"Juryen","audio":"jury1.m4a"},"meanings":[{"examples":[{"example":"d'Membere vum Jury hunn dem Kandidat schwéier Froe gestallt","usage":"ALLG"}],"synonyms":[],"translations":[{"language":"ALL","translation":"Jury","complement":"Prüfungskommission, Preisgericht"},{"language":"FR","translation":"jury","complement":"d'un concours, d'un examen, d'une compétition"},{"language":"PO","translation":"júri","complement":"de um concurso, de um exame, de uma competição"},{"language":"EN","translation":"jury","complement":"of an exam, of a competition"}]}]}]}