{"id":"ef6387402e77012a8e7a7cfae27effb0","word":"asammelen","types":[{"type":"verb","lodKey":"ASAMMELEN1","details":{"auxiliaryVerb":"HUNN","pastParticiples":["agesammelt"],"verbCategory":"VRB","audio":"asammelen1.m4a"},"meanings":[{"examples":[{"example":"hien huet déi eidel Fläschen agesammelt","usage":"ALLG"},{"example":"d'Joffer sammelt de Kanner hir Hefter an","usage":"ALLG"},{"example":"d'Stëmmziedele si vum Huissier agesammelt ginn","usage":"ALLG"}],"synonyms":[],"reflexivePronoun":"TRANSITIF","employsImpersonal":"VRB-EMPL-IMPERS-IMPOSS","translations":[{"language":"ALL","translation":"einsammeln"},{"language":"FR","translation":"ramasser"},{"language":"PO","translation":"apanhar"},{"language":"EN","translation":"to collect","complement":"to pick up, to take in"}]}]}]}