{"id":"f7080a7aad0edd23c22427cddd4c2003","word":"Eed","types":[{"type":"noun","lodKey":"EED1","details":{"nounGender":"M","nounCategory":"SUBST","plural":"Eeden","audio":"eed1.m4a"},"meanings":[{"examples":[{"example":"den Zeien huet um Geriicht ënner Eed ausgesot","usage":"ALLG"}],"synonyms":[],"translations":[{"language":"ALL","translation":"Eid"},{"language":"FR","translation":"serment"},{"language":"PO","translation":"juramento"},{"language":"EN","translation":"oath","complement":"promise"}]},{"examples":[{"example":"de Keessjee ass wéinst engem falschen Eed ugeklot ginn","usage":"ALLG"}],"synonyms":[],"polyLex":"falschen Eed","translations":[{"language":"ALL","translation":"Meineid"},{"language":"FR","translation":"parjure"},{"language":"PO","translation":"perjúrio"},{"language":"EN","translation":"perjury"}]}]}]}