{"id":"ff20f353bb6a46723f4001817247026f","word":"didaktesch","types":[{"type":"adjective","lodKey":"DIDAKTESCH1","details":{"audio":"didaktesch1.m4a"},"meanings":[{"examples":[{"example":"d'Fachkenntnesser soen näischt iwwer dem Kandidat seng didaktesch Fäegkeeten aus","usage":"ALLG"},{"example":"eis Schoul huet neit didaktescht Material kritt","usage":"ALLG"},{"example":"dat Buch ass didaktesch wäertvoll","usage":"ALLG"}],"synonyms":[],"translations":[{"language":"ALL","translation":"didaktisch"},{"language":"FR","translation":"didactique"},{"language":"PO","translation":"didático"},{"language":"EN","translation":"didactic"}]}]}]}