{"id":"0928edac4ecd887af64fd4b84b5be1b0","word":"auslaachen","types":[{"type":"verb","details":{"auxiliaryVerb":"HUNN","pastParticiples":["ausgelaacht"]},"meanings":[{"lodKey":"AUSLAACHEN1","examples":[{"example":"hie auslaachenverspott an","usage":"ALLG"},{"example":"du en och auslaachen, wéi e vum Stull gefall ass?","usage":"ALLG"}],"synonyms":[],"translations":[{"language":"ALL","translation":"auslachen","complement":"lachen über"},{"language":"FR","translation":"rire de","complement":"pour se moquer"},{"language":"PO","translation":"rir-se de","complement":"fazer troça de"},{"language":"EN","translation":"to laugh at"}]}]}]}