{"id":"0eb77104b5c979e56611b3ab8cf73623","word":"Angab","types":[{"type":"noun","lodKey":"ANGAB1","details":{"nounGender":"F","plural":"Angaben"},"meanings":[{"examples":[{"example":"d'Schülerin huet d' Angabfalsch ofgeschriwwen","usage":"ALLG"},{"example":"de Problem konnt net geléist ginn, well eng Angabgefeelt huet","usage":"ALLG"}],"synonyms":[],"translations":[{"language":"ALL","translation":"Angabe","complement":"Fragestellung"},{"language":"FR","translation":"donnée","complement":"d'un problème"},{"language":"PO","translation":"dado","complement":"de um problema"},{"language":"EN","translation":"instruction","complement":"necessary to complete a task"}]},{"examples":[{"example":"dem Zeie sengen Angabno kann den Ugekloten net schëlleg sinn","usage":"ALLG"}],"synonyms":[],"translations":[{"language":"ALL","translation":"Angabe","complement":"Mitteilung"},{"language":"FR","translation":"déclaration","complement":"dires"},{"language":"PO","translation":"declaração","complement":"depoimento"},{"language":"EN","translation":"statement","complement":"declaration, testimony"}]}]}]}