{"id":"0f085d5c473bdf3c7ce796bb647379c2","word":"Beootmungsapparat","types":[{"type":"noun","lodKey":"BEOOTMUNGSAPPARAT1","details":{"nounGender":"M","plural":"Beootmungsapparaten","audio":"beootmungsapparat1.m4a"},"meanings":[{"examples":[{"example":"d'Spidol gouf mat 25 zousätzleche Beootmungsapparater ekipéiert","usage":"ALLG"}],"synonyms":[],"translations":[{"language":"ALL","translation":"Beatmungsgerät"},{"language":"FR","translation":"respirateur artificiel"},{"language":"PO","translation":"respirador artificial"},{"language":"EN","translation":"ventilator","complement":"medical"}]}]}]}