{"id":"10d8aba99a920becdebd64be9605d357","word":"Kannerklinick","types":[{"type":"noun","lodKey":"KANNERKLINICK1","details":{"nounGender":"F","plural":"Kannerklinicken","audio":"kannerklinick1.m4a"},"meanings":[{"examples":[{"example":"um 112 krut ech geroden, mat eisem Klengen an eng Kannerklinick ze fueren","usage":"ALLG"}],"synonyms":[],"translations":[{"language":"ALL","translation":"Kinderklinik"},{"language":"FR","translation":"hôpital pour enfants"},{"language":"PO","translation":"hospital pediátrico"},{"language":"EN","translation":"paediatric clinic"}]}]}]}