{"id":"1a87c6b8429a077109f45e9c8881a316","word":"Kierchen","types":[{"type":"noun","lodKey":"KIERCHEN1","details":{"nounGender":"N","nounCategory":"NOM-PROPRE","audio":"kierchen1.m4a"},"meanings":[{"examples":[{"example":"ech wunnen zu Kierchen","usage":"ALLG"},{"example":"fiert dëse Bus op Kierchen ?","usage":"ALLG"}],"synonyms":[],"translations":[{"language":"ALL","translation":"Niederbesslingen"},{"language":"FR","translation":"Basbellain"},{"language":"PO","translation":"Basbellain"},{"language":"EN","translation":"Basbellain"}]}]}]}