{"id":"1fb529abd09810685d301dbc17742736","word":"Loscht","types":[{"type":"noun","details":{"nounGender":"F"},"meanings":[{"lodKey":"LOSCHT1","examples":[{"example":"ech hätt nawell Loschtop e Stéck Taart!","usage":"ALLG"},{"example":"hues de keng Loscht, mat mir an d'Stad ze goen?","usage":"ALLG"},{"example":"bei där Aarbecht ass mir all Loschtvergaangen","usage":"ALLG"}],"synonyms":[],"translations":[{"language":"ALL","translation":"Lust","complement":"Verlangen"},{"language":"FR","translation":"envie","complement":"désir"},{"language":"PO","translation":"vontade","complement":"desejo, gosto"},{"language":"EN","translation":"fancy","complement":"wish"}]}]}]}