{"id":"268e8fcc8703650c3bbc156bfcea8f84","word":"jëtzeg","types":[{"type":"adjective","lodKey":"JETZEG1","details":{"audio":"jetzeg1.m4a"},"meanings":[{"examples":[{"example":"déi jëtzeg Regierung wëllt méi staark géint den illegale Waffenhandel virgoen","usage":"ALLG"},{"example":"zum jëtzegen Zäitpunkt wësse mer nach net, wéi d'Walen ausginn","usage":"ALLG"}],"synonyms":[],"translations":[{"language":"ALL","translation":"jetzig"},{"language":"FR","translation":"actuel"},{"language":"PO","translation":"atual"},{"language":"EN","translation":"current"}]}]}]}