{"id":"2af77e6a76a4bb6e1243914718bd3061","word":"ukloen","types":[{"type":"verb","lodKey":"UKLOEN1","details":{"auxiliaryVerb":"HUNN","pastParticiples":["ugeklot"],"audio":"ukloen1.m4a"},"meanings":[{"examples":[{"example":"de Parquet ukloenhie wéinst Mord","usage":"ALLG"},{"example":"déi zwee Beamte ukloenwéinst Korruptioun","usage":"ALLG"}],"synonyms":[],"reflexivePronoun":"TRANSITIF","employsImpersonal":"VRB-EMPL-IMPERS-IMPOSS","translations":[{"language":"ALL","translation":"anklagen","complement":"vor Gericht"},{"language":"FR","translation":"inculper"},{"language":"PO","translation":"acusar","complement":"em tribunal"},{"language":"EN","translation":"to charge","complement":"with a crime"}]}]}]}