{"id":"301b77371ab6345e21f86d1977562710","word":"duerchpëtzen","types":[{"type":"verb","lodKey":"DUERCHPETZEN1","details":{"auxiliaryVerb":"HUNN","pastParticiples":["duerchgepëtzt"]},"meanings":[{"examples":[{"example":"no laangem Iwwerleeën duerchpëtzenmäi Papp um Enn awer dee falsche Kabel","usage":"ALLG"}],"synonyms":[],"translations":[{"language":"ALL","translation":"(mit einer Zange) durchtrennen"},{"language":"FR","translation":"sectionner","complement":"avec une pince"},{"language":"PO","translation":"cortar","complement":"com um alicate"},{"language":"EN","translation":"to sever","complement":"with pincers"}]}]}]}