{"id":"34979f19880e12cdec01db54fd86c6fe","word":"Verlängerung","types":[{"type":"noun","details":{"nounGender":"F","plural":"Verlängerungen"},"meanings":[{"lodKey":"VERLANGERUNG1","examples":[{"example":"d' Verlängerungvun der Landepist um Flughafe gouf geneemegt","usage":"ALLG"}],"synonyms":[],"translations":[{"language":"ALL","translation":"Verlängerung","complement":"räumliche Ausdehnung"},{"language":"FR","translation":"prolongement","complement":"dans l'espace"},{"language":"PO","translation":"prolongamento","complement":"no espaço"},{"language":"EN","translation":"extension","complement":"spatial"}]},{"lodKey":"VERLANGERUNG1","examples":[{"example":"d'Ministesch schléit eng Verlängerungvun der obligatorescher Schoulzäit vir","usage":"ALLG"}],"synonyms":[],"translations":[{"language":"ALL","translation":"Verlängerung","complement":"zeitliche Ausdehnung"},{"language":"FR","translation":"prolongation","complement":"dans le temps"},{"language":"PO","translation":"prolongamento","complement":"no tempo"},{"language":"EN","translation":"extension","complement":"temporally"}]},{"lodKey":"VERLANGERUNG1","examples":[{"example":"hues de dech schonn ëm d' Verlängerungvun dengem Fürerschäi gekëmmert?","usage":"ALLG"}],"synonyms":[],"translations":[{"language":"ALL","translation":"Verlängerung","complement":"der Laufzeit, der Gültigkeit"},{"language":"FR","translation":"prolongement (de la validité)"},{"language":"PO","translation":"revalidação","complement":"prolongamento da validade"},{"language":"EN","translation":"extension","complement":"of a period, of validity"}]},{"lodKey":"VERLANGERUNG1","examples":[{"example":"beim Fussball dauert d' Verlängerungzweemol eng Véierelstonn","usage":"ALLG"},{"example":"no 90 Minutten ass de Match an d' Verlängerunggaangen","usage":"ALLG"}],"synonyms":[],"translations":[{"language":"ALL","translation":"Verlängerung","complement":"der Spielzeit"},{"language":"FR","translation":"prolongation","complement":"d'un match"},{"language":"PO","translation":"prolongamento","complement":"de jogo"},{"language":"EN","translation":"extra time","complement":"in sport"}]},{"lodKey":"VERLANGERUNG1","examples":[{"example":"de Kabel vun der Buermaschinn ass ze kuerz, géi sich eng Verlängerung!","usage":"ALLG"}],"synonyms":[],"translations":[{"language":"ALL","translation":"Verlängerungskabel"},{"language":"FR","translation":"rallonge","complement":"câble"},{"language":"PO","translation":"extensão (elétrica)"},{"language":"EN","translation":"extension (lead)"}]}]}]}