{"id":"3730c9866421d81473613698c0c0ac4f","word":"Course","types":[{"type":"noun","lodKey":"COURSE1","details":{"nounGender":"F","plural":"Courssen"},"meanings":[{"examples":[{"example":"ech si bei der Courseals Drëtten iwwer d'Arrivée gefuer","usage":"ALLG"},{"example":"de Leefer huet dëst Joer un iwwer zéng Coursedeelgeholl","usage":"ALLG"},{"example":"d'Kanner maachen eng Course, wien de Kakao fir d'éischt gedronk huet","usage":"ALLG"}],"synonyms":[],"translations":[{"language":"ALL","translation":"Rennen"},{"language":"FR","translation":"course","complement":"épreuve sportive"},{"language":"PO","translation":"corrida","complement":"prova desportiva"},{"language":"EN","translation":"race","complement":"competition"}]}]}]}