{"id":"3e0f182c122e990629b3e5917037c606","word":"ëmhaen","types":[{"type":"verb","details":{"auxiliaryVerb":"HUNN","pastParticiples":["ëmgehaen"]},"meanings":[{"lodKey":"EMHAEN1","examples":[{"example":"déi grouss Dänn am Park ëmhaenmuer","usage":"ALLG"}],"synonyms":[],"translations":[{"language":"ALL","translation":"fällen","complement":"einen Baum"},{"language":"FR","translation":"abattre","complement":"un arbre"},{"language":"PO","translation":"abater","complement":"uma árvore"},{"language":"EN","translation":"to fell","complement":"a tree"}]}]}]}