{"id":"428703a9485ad2e8d372fb746c77969e","word":"Bless","types":[{"type":"noun","lodKey":"BLESS1","details":{"nounGender":"F","nounCategory":"SUBST","plural":"Blessen","audio":"bless1.m4a"},"meanings":[{"examples":[{"example":"d'Kand huet eng Blessum Aarm, well et gefall ass","usage":"ALLG"}],"synonyms":[],"translations":[{"language":"ALL","translation":"Schramme","complement":"Verletzung"},{"language":"FR","translation":"écorchure"},{"language":"PO","translation":"esfoladela"},{"language":"EN","translation":"scratch"}]}]},{"type":"noun","lodKey":"BLESS2","details":{"nounGender":"M","nounCategory":"SUBST","audio":"bless2.m4a"},"meanings":[{"examples":[{"example":"hiren Hengscht huet e Bless","usage":"ALLG"}],"synonyms":[],"translations":[{"language":"ALL","translation":"Blesse","complement":"Stirnfleck"},{"language":"FR","translation":"tache blanche","complement":"sur le chanfrein des chevaux et des bovins"},{"language":"PO","translation":"estrela","complement":"na testa dos cavalos e dos bovinos"},{"language":"EN","translation":"blaze","complement":"mark"}]}]}]}