{"id":"45d3e48492e31f3e83933f518e9b3980","word":"Deckelstaart","types":[{"type":"noun","lodKey":"DECKELSTAART1","details":{"nounGender":"F","plural":"Deckelstaarten","audio":"deckelstaart1.m4a"},"meanings":[{"examples":[{"example":"mir hunn eise Gäscht beim Kaffi e Stéck Deckelstaartzerwéiert","usage":"ALLG"}],"synonyms":[],"translations":[{"language":"ALL","translation":"gedeckter Apfelkuchen"},{"language":"FR","translation":"tarte couverte aux pommes"},{"language":"PO","translation":"tarte de maçã coberta"},{"language":"EN","translation":"apple pie"}]}]}]}