{"id":"50547ce62e0b180040efe276c74882f1","word":"festhalen","types":[{"type":"verb","details":{"auxiliaryVerb":"HUNN","pastParticiples":["festgehalen","festgehal"]},"meanings":[{"lodKey":"FESTHALEN1","examples":[{"example":"d'Touriste festhalenméi ewéi sechs Stonnen op der Grenz","usage":"ALLG"}],"synonyms":[],"translations":[{"language":"ALL","translation":"festhalten","complement":"zurückhalten"},{"language":"FR","translation":"retenir","complement":"arrêter, bloquer"},{"language":"PO","translation":"reter","complement":"parar, bloquear"},{"language":"EN","translation":"to detain"}]},{"lodKey":"FESTHALEN1","examples":[{"example":"de Kommitee festhalen, datt no all Sëtzung e Rapport geschriwwe gëtt","usage":"ALLG"}],"synonyms":[],"translations":[{"language":"ALL","translation":"festhalten","complement":"beschließen"},{"language":"FR","translation":"décider"},{"language":"PO","translation":"decidir"},{"language":"EN","translation":"to decide"}]},{"lodKey":"FESTHALEN1","examples":[{"example":"de Fotograf festhalendee wonnerschéine Sonnenënnergang am Bild","usage":"ALLG"}],"synonyms":[],"translations":[{"language":"ALL","translation":"festhalten","complement":"im Bild, schriftlich"},{"language":"FR","translation":"fixer","complement":"par écrit"},{"language":"PO","translation":"fixar","complement":"por escrito"},{"language":"EN","translation":"to capture"}]},{"lodKey":"FESTHALEN1","examples":[{"example":"d'Duerfveräiner festhalenun alen Traditioune","usage":"ALLG"},{"example":"trotz staarke Protester wëllt d'Regierung un der Reform festhalen","usage":"ALLG"}],"synonyms":[],"translations":[{"language":"ALL","translation":"festhalten an"},{"language":"FR","translation":"rester fidèle à"},{"language":"PO","translation":"manter-se fiel a"},{"language":"EN","translation":"to adhere to"}]}]}]}