{"id":"551810d75613510ccf820988d016261a","word":"Ofléisung","types":[{"type":"noun","lodKey":"OFLEISUNG1","details":{"nounGender":"F","plural":"Ofléisungen","audio":"ofleisung1.m4a"},"meanings":[{"examples":[{"example":"bei der Ofléisungvun der Gard ware vill Touristen do","usage":"ALLG"}],"synonyms":[],"translations":[{"language":"ALL","translation":"Ablösung","complement":"das Ablösen"},{"language":"FR","translation":"relève","complement":"remplacement"},{"language":"PO","translation":"revezamento"},{"language":"EN","translation":"changing","complement":"of a guard, of a sentry"}]}]}]}