{"id":"5b102e2ed051a87f3fbe48e852cc0d4f","word":"Aarbechtssëtzung","types":[{"type":"noun","lodKey":"AARBECHTSSETZUNG1","details":{"nounGender":"F","plural":"Aarbechtssëtzungen","audio":"aarbechtssetzung1.m4a"},"meanings":[{"examples":[{"example":"eis Aarbechtssëtzung huet méi laang gedauert ewéi geplangt","usage":"ALLG"}],"synonyms":[],"translations":[{"language":"ALL","translation":"Arbeitssitzung"},{"language":"FR","translation":"séance de travail"},{"language":"PO","translation":"sessão de trabalho"},{"language":"EN","translation":"working session"}]}]}]}