{"id":"755c0cfa770e9bf02980d6721bf188d7","word":"Décke_Kräizschniewel","types":[{"type":"noun","details":{"nounGender":"M","plural":"Déck Kräizschniewelen"},"meanings":[{"lodKey":"DECKEKRAIZSCHNIEWEL1","examples":[{"example":"wéi laang bréien d' Décke_Kräizschniewel?","usage":"ALLG"}],"synonyms":[],"translations":[{"language":"ALL","translation":"Kiefernkreuzschnabel"},{"language":"FR","translation":"bec-croisé perroquet"},{"language":"PO","translation":"cruza-bico-papagaio"},{"language":"EN","translation":"parrot crossbill"}]}]}]}