{"id":"7b5b91a26263c62fdd7835bb596d2689","word":"Grondhaff","types":[{"type":"noun","lodKey":"GRONDHAFF1","details":{"nounGender":"N","nounCategory":"NOM-PROPRE","audio":"grondhaff1.m4a"},"meanings":[{"examples":[{"example":"ech wunnen um Grondhaff","usage":"ALLG"},{"example":"fiert dëse Bus op de Grondhaff?","usage":"ALLG"}],"synonyms":[],"translations":[{"language":"ALL","translation":"Grundhof"},{"language":"FR","translation":"Grundhof"},{"language":"PO","translation":"Grundhof"},{"language":"EN","translation":"Grundhof"}]}]}]}