{"id":"7e8ac6998943b0b42c98a4a909238fc8","word":"riicht zéien","types":[{"type":"verb","details":{"auxiliaryVerb":"HUNN","pastParticiples":["riicht gezunn"]},"meanings":[{"lodKey":"RIICHTZEIEN1","examples":[{"example":"d'Jupe nach riicht zéien, éier s de erausgees, se ass e bësse gekniwwelt!","usage":"ALLG"},{"example":"d'Napp muss nach riicht zéienginn, éier den Dësch ka gedeckt ginn","usage":"ALLG"}],"synonyms":[],"translations":[{"language":"ALL","translation":"geradeziehen"},{"language":"FR","translation":"lisser","complement":"aplatir"},{"language":"PO"},{"language":"EN","translation":"to smooth down"}]}]}]}