{"id":"80e784c23ebf190832916ca4476ca5bc","word":"Concierge","types":[{"type":"noun","details":{"nounGender":"M","plural":"Conciergen"},"meanings":[{"lodKey":"CONCIERGE1","examples":[{"example":"de Conciergesuergt derfir, datt am Gebai ëmmer alles an der Rei ass","usage":"ALLG"}],"synonyms":[],"translations":[{"language":"ALL","translation":"Hausmeister"},{"language":"FR","translation":"concierge"},{"language":"PO","translation":"porteiro"},{"language":"EN","translation":"porter"}]}]},{"type":"noun","details":{"nounGender":"F","plural":"Conciergen"},"meanings":[]}]}