{"id":"847cc0e11d8973971da0ca0d388f3f1c","word":"Unhaltspunkt","types":[{"type":"noun","lodKey":"UNHALTSPUNKT1","details":{"nounGender":"M","plural":"Unhaltspunkten","audio":"unhaltspunkt1.m4a"},"meanings":[{"examples":[{"example":"d'Kierch ass e gudden Unhaltspunkt, fir sech ze orientéieren","usage":"ALLG"}],"synonyms":[],"translations":[{"language":"ALL","translation":"Orientierungspunkt"},{"language":"FR","translation":"(point de) repère"},{"language":"PO","translation":"(ponto de) referência"},{"language":"EN","translation":"reference point"}]},{"examples":[{"example":"et gëtt keen Unhaltspunkt, wou déi vermësste Persoun kéint sinn","usage":"ALLG"}],"synonyms":[],"translations":[{"language":"ALL","translation":"Anhaltspunkt"},{"language":"FR","translation":"indication","complement":"d'information"},{"language":"PO","translation":"indicação","complement":"de informação"},{"language":"EN","translation":"clue"}]}]}]}