{"id":"87978042e1411f94f4ccda6d03d3d71d","word":"Gellecht","types":[{"type":"noun","details":{"nounGender":"F"},"meanings":[{"lodKey":"GELLECHT1","examples":[{"example":"et war eng Gellecht, fir hinne beim Danzen nozekucken","usage":"ALLG"}],"synonyms":[],"translations":[{"language":"ALL","translation":"Genuss"},{"language":"FR","translation":"plaisir","complement":"pour les sens"},{"language":"PO","translation":"prazer","complement":"para os sentidos"},{"language":"EN","translation":"pleasure"}]}]}]}