{"id":"8f5c40db0209e4286054733ef8e6be6d","word":"Erpressung","types":[{"type":"noun","lodKey":"ERPRESSUNG1","details":{"nounGender":"F","nounCategory":"SUBST","plural":"Erpressungen","audio":"erpressung1.m4a"},"meanings":[{"examples":[{"example":"si goufen d'Affer vun enger Erpressung","usage":"ALLG"}],"synonyms":[],"translations":[{"language":"ALL","translation":"Erpressung"},{"language":"FR","translation":"chantage"},{"language":"PO","translation":"chantagem"},{"language":"EN","translation":"blackmail"}]}]}]}