{"id":"903d8cb7d46553d6e54066309fc0c06a","word":"Bobinn","types":[{"type":"noun","lodKey":"BOBINN1","details":{"nounGender":"F","nounCategory":"SUBST","plural":"Bobinnen","audio":"bobinn1.m4a"},"meanings":[{"examples":[{"example":"d' Bobinnass bal eidel","usage":"ALLG"},{"example":"d'Mamm keeft zwou BobinnZwier","usage":"ALLG"}],"synonyms":[],"translations":[{"language":"ALL","translation":"Spule"},{"language":"FR","translation":"bobine"},{"language":"PO","translation":"bobina"},{"language":"EN","translation":"reel"}]}]}]}