{"id":"94b7f4e6955f935e13a70f7452f76e07","word":"revendiquéieren","types":[{"type":"verb","lodKey":"REVENDIQUEIEREN1","details":{"auxiliaryVerb":"HUNN","pastParticiples":["revendiquéiert"]},"meanings":[{"examples":[{"example":"d'Aarbechter vun eiser Firma hunn net gezéckt, fir hir Rechter ze revendiquéieren","usage":"ALLG"}],"synonyms":[],"reflexivePronoun":"TRANSITIF","employsImpersonal":"VRB-EMPL-IMPERS-IMPOSS","translations":[{"language":"ALL","translation":"einfordern"},{"language":"FR","translation":"revendiquer","complement":"réclamer, exiger"},{"language":"PO","translation":"reivindicar","complement":"reclamar, exigir"},{"language":"EN","translation":"to demand"}]}]}]}