{"id":"98e8abfd0452a82546b4b5af2fbe179b","word":"Raséierapparat","types":[{"type":"noun","details":{"nounGender":"M","plural":"Raséierapparaten"},"meanings":[{"lodKey":"RASEIERAPPARAT1","examples":[{"example":"mäi Papp hëlt léiwer de Raséierapparatewéi d'Gillette","usage":"ALLG"}],"synonyms":[],"translations":[{"language":"ALL","translation":"(elektrische(r)) Rasierapparat"},{"language":"FR","translation":"rasoir (électrique)"},{"language":"PO","translation":"máquina de barbear"},{"language":"EN","translation":"electric razor"}]}]}]}