{"id":"9b86360cc594a2ed7d55b2f6df6910d9","word":"Palett","types":[{"type":"noun","details":{"nounGender":"F","plural":"Paletten"},"meanings":[{"lodKey":"PALETT1","examples":[{"example":"eisen neie Camion huet e Gräifaarm, fir d' Palettop- an ofzelueden","usage":"ALLG"},{"example":"mir kruten dräi PalettPlättercher geliwwert","usage":"ALLG"}],"synonyms":[],"translations":[{"language":"ALL","translation":"Palette","complement":"für Stapelgüter"},{"language":"FR","translation":"palette","complement":"de chargement"},{"language":"PO","translation":"palete","complement":"de carregamento"},{"language":"EN","translation":"pallet","complement":"for loads"}]},{"lodKey":"PALETT1","examples":[{"example":"de Musée stellt d' Palettvun e puer bekannte Moler aus","usage":"ALLG"}],"synonyms":[],"translations":[{"language":"ALL","translation":"Palette","complement":"zum Farbenmischen"},{"language":"FR","translation":"palette","complement":"de peintre"},{"language":"PO","translation":"paleta","complement":"de pintor"},{"language":"EN","translation":"palette","complement":"for mixing paint"}]},{"lodKey":"PALETT1","examples":[{"example":"d'Vendeuse huet eis eng ganz PalettKaffismaschinne gewisen","usage":"ALLG"}],"synonyms":[],"translations":[{"language":"ALL","translation":"Palette","complement":"Vielfalt"},{"language":"FR","translation":"palette","complement":"gamme"},{"language":"PO","translation":"gama"},{"language":"EN","translation":"range"}]}]}]}