{"id":"a1019013a8e83dc88e0f26b85f7df867","word":"freeën","types":[{"type":"verb","details":{"auxiliaryVerb":"HUNN","pastParticiples":["gefreet"]},"meanings":[{"lodKey":"FREEEN1","examples":[{"example":"et freeëneis","usage":"ALLG"}],"synonyms":[],"translations":[{"language":"ALL","translation":"freuen"},{"language":"FR","translation":"réjouir"},{"language":"PO","translation":"fazer prazer a"},{"language":"EN","translation":"to be pleased"}]},{"lodKey":"FREEEN1","examples":[{"example":"d'Grousselteren freeënsech iwwer eise Besuch","usage":"ALLG"},{"example":"wa meng Schwëster dat héiert, da wäert se sech freeën!","usage":"ALLG"}],"synonyms":[],"translations":[{"language":"ALL","translation":"sich freuen (über)"},{"language":"FR","translation":"se réjouir (de)"},{"language":"PO","translation":"ficar muito contente (com)"},{"language":"EN","translation":"to be pleased (about)"}]},{"lodKey":"FREEEN1","examples":[{"example":"d'Kanner freeënsech op Niklosdag","usage":"ALLG"},{"example":"no véierzeg Déngschtjore freeënech mech elo op meng Pensioun","usage":"ALLG"}],"synonyms":[],"translations":[{"language":"ALL","translation":"sich freuen auf"},{"language":"FR","translation":"attendre avec impatience"},{"language":"PO","translation":"esperar com ansiedade"},{"language":"EN","translation":"to look forward to"}]}]}]}