{"id":"a37fd444ae81aeeea9218f35d8ad5217","word":"Strass","types":[{"type":"noun","lodKey":"STRASS1","details":{"nounGender":"F","plural":"Strassen"},"meanings":[{"examples":[{"example":"ech hunn d' Strassdréchen, ech muss eppes drénken","usage":"EGS"},{"example":"vum ville Jäizen hunn ech d' Strasswéi","usage":"EGS"},{"example":"zanter gëschter hunn ech d' Strasswéi, wann ech schlécken","usage":"EGS"}],"synonyms":[],"translations":[{"language":"ALL","translation":"Kehle","complement":"Rachen"},{"language":"FR","translation":"gorge"},{"language":"PO","translation":"garganta","complement":"laringe, faringe"},{"language":"EN","translation":"throat","complement":"larynx, pharynx"}]}]}]}