{"id":"ab5b14d2570fdaa6b7f1e5be19e469d6","word":"Leed","types":[{"type":"noun","lodKey":"LEED1","details":{"nounGender":"N"},"meanings":[{"examples":[{"example":"et gëtt vill Leedan der Welt","usage":"ALLG"}],"synonyms":[],"translations":[{"language":"ALL","translation":"Not"},{"language":"FR","translation":"misère","complement":"détresse, souffrance"},{"language":"PO","translation":"miséria","complement":"desgraça, sofrimento"},{"language":"EN","translation":"misery"}]},{"examples":[{"example":"d'Meedchen huet him all säi Leedgeklot","usage":"ALLG"}],"synonyms":[],"translations":[{"language":"ALL","translation":"Leid","complement":"Kummer"},{"language":"FR","translation":"chagrin"},{"language":"PO","translation":"mágoa"},{"language":"EN","translation":"sorrow"}]},{"examples":[{"example":"mir waren därmoossen am Leed, well der net erbäikomm sidd!","usage":"ALLG"}],"synonyms":[],"polyLex":"am Leed sinn","translations":[{"language":"ALL","translation":"besorgt sein"},{"language":"FR","translation":"être préoccupé"},{"language":"PO","translation":"estar preocupado"},{"language":"EN","translation":"to be worried"}]}]}]}