{"id":"b78ff10a38d3bfccbfefc57cf7f09d95","word":"Kleng_Baartfliedermaus","types":[{"type":"noun","details":{"nounGender":"F","plural":"Kleng Baartfliedermais"},"meanings":[{"lodKey":"KLENGBAARTFLIEDERMAUS1","examples":[{"example":"d' Kleng_Baartfliedermausass eng vun de klengsten an am meeschte verbreete Fliedermausaarten zu Lëtzebuerg","usage":"ALLG"}],"synonyms":[],"translations":[{"language":"ALL","translation":"Kleine Bartfledermaus"},{"language":"FR","translation":"murin à moustaches"},{"language":"PO","translation":"morcego-de-bigodes"},{"language":"EN","translation":"whiskered bat"}]}]}]}