{"id":"b9e19033628d1592942af80f17154d72","word":"intransitiv","types":[{"type":"adjective","lodKey":"INTRANSITIV1","details":{"audio":"intransitiv1.m4a"},"meanings":[{"examples":[{"example":"Verbe kann een net an de Passiv setzen intransitiv","usage":"ALLG"},{"example":"d'Verb „drénken“ gëtt och intransitivbenotzt","usage":"ALLG"}],"synonyms":[],"translations":[{"language":"ALL","translation":"intransitiv"},{"language":"FR","translation":"intransitif"},{"language":"PO","translation":"intransitivo"},{"language":"EN","translation":"intransitive"}]}]}]}