{"id":"c911e13a66bed7a612f6f0d3fd5707c0","word":"Facturéierung","types":[{"type":"noun","lodKey":"FACTUREIERUNG1","details":{"nounGender":"F","nounCategory":"SUBST","plural":"Facturéierungen"},"meanings":[{"examples":[{"example":"bei der Facturéierungvun den Ersatzstécker huet de Comptabel sech geiert","usage":"ALLG"}],"synonyms":[],"translations":[{"language":"ALL","translation":"Inrechnungstellung"},{"language":"FR","translation":"facturation","complement":"établissement d'une facture"},{"language":"PO","translation":"faturação","complement":"elaboração de uma fatura"},{"language":"EN","translation":"invoicing"}]}]}]}