{"id":"cbebc6b8756ee0c72692ba84b54a6e30","word":"Hämorrhoid","types":[{"type":"noun","lodKey":"HAMORRHOID1","details":{"nounGender":"F","plural":"Hämorrhoiden","audio":"hamorrhoid1.m4a"},"meanings":[{"examples":[{"example":"bei haardem Stullgang féiert fest ze drécken dacks zu Hämorrhoid","usage":"ALLG"}],"synonyms":[],"translations":[{"language":"ALL","translation":"Hämorrhoide"},{"language":"FR","translation":"hémorroïde"},{"language":"PO","translation":"hemorroida"},{"language":"EN","translation":"haemorrhoid"}]}]}]}