{"id":"d2361cb3bbdd0b60ba8a61b4b1285ea6","word":"Rommeler_Haff","types":[{"type":"noun","details":{"nounGender":"N"},"meanings":[{"lodKey":"ROMMELERHAFF1","examples":[{"example":"ech wunnen um Rommeler_Haff","usage":"ALLG"},{"example":"fiert dëse Bus op de Rommeler_Haff?","usage":"ALLG"}],"synonyms":[],"translations":[{"language":"ALL","translation":"Martelinville"},{"language":"FR","translation":"Martelinville"},{"language":"PO","translation":"Martelinville"},{"language":"EN","translation":"Martelinville"}]}]}]}