{"id":"d5a6292ca87ea4d30a3a99ac15b4a463","word":"ausschlaggeebend","types":[{"type":"adjective","details":{},"meanings":[{"lodKey":"AUSSCHLAGGEEBEND1","examples":[{"example":"fir mech ass just de Präis ausschlaggeebend","usage":"ALLG"},{"example":"seng Meenung däerf net eleng ausschlaggeebendsinn!","usage":"ALLG"},{"example":"de Facteur Zäit ass ausschlaggeebendbei engem Häerzinfarkt","usage":"ALLG"}],"synonyms":[],"translations":[{"language":"ALL","translation":"ausschlaggebend"},{"language":"FR","translation":"déterminant"},{"language":"PO","translation":"determinante"},{"language":"EN","translation":"determining"}]}]}]}