{"id":"dccb2ad23b0c4d733d8ec450ee65a6cc","word":"zeréckfroen","types":[{"type":"verb","lodKey":"ZERECKFROEN1","details":{"auxiliaryVerb":"HUNN","pastParticiples":["zeréckgefrot"]},"meanings":[{"examples":[{"example":"kéints de meng Bicher bei denger Schwëster zeréckfroen?","usage":"ALLG"},{"example":"e Kaddo zeréckfroeneen net","usage":"ALLG"}],"synonyms":[],"reflexivePronoun":"TRANSITIF","employsImpersonal":"VRB-EMPL-IMPERS-IMPOSS","translations":[{"language":"ALL","translation":"zurückerbitten"},{"language":"FR","translation":"réclamer","complement":"redemander pour récupérer"},{"language":"PO","translation":"pedir de volta"},{"language":"EN","translation":"to ask for something back"}]}]}]}