{"id":"dd072ae5d2feb7530c24a0666c22d6e3","word":"Grousse Wakeleefer","types":[{"type":"noun","details":{"nounGender":"M","plural":"Grouss Wakeleefer"},"meanings":[{"lodKey":"GROUSSEWAKELEEFER1","examples":[{"example":"wéi laang bréien d' Grousse Wakeleefer?","usage":"ALLG"}],"synonyms":[],"translations":[{"language":"ALL","translation":"Sandregenpfeifer"},{"language":"FR","translation":"pluvier grand-gravelot"},{"language":"PO","translation":"borrelho-grande-de-coleira"},{"language":"EN","translation":"common ringed plover"}]}]}]}