{"id":"de8884a0d564f67f62abae6a58f34bb5","word":"restrukturéieren","types":[{"type":"verb","lodKey":"RESTRUKTUREIEREN1","details":{"auxiliaryVerb":"HUNN","pastParticiples":["restrukturéiert"]},"meanings":[{"examples":[{"example":"wann eise Betrib restrukturéieren, si vill Aarbechtsplazen a Gefor","usage":"ALLG"}],"synonyms":[],"reflexivePronoun":"TRANSITIF","employsImpersonal":"VRB-EMPL-IMPERS-IMPOSS","translations":[{"language":"ALL","translation":"restrukturieren"},{"language":"FR","translation":"restructurer"},{"language":"PO","translation":"reestruturar"},{"language":"EN","translation":"to restructure"}]}]}]}