{"id":"e0737c972e0bf6fdb4c3991f547febfd","word":"bekrichen","types":[{"type":"verb","lodKey":"BEKRICHEN1","details":{"auxiliaryVerb":"HUNN","pastParticiples":["bekricht"],"verbCategory":"VRB"},"meanings":[{"examples":[{"example":"déi zwee Länner bekrichensech jorelaang","usage":"ALLG"}],"synonyms":[],"reflexivePronoun":"PRONOM","employsImpersonal":"VRB-EMPL-IMPERS-IMPOSS","translations":[{"language":"ALL","translation":"sich bekriegen"},{"language":"FR","translation":"se faire la guerre"},{"language":"PO","translation":"guerrear-se"},{"language":"EN","translation":"to make war on"}]}]}]}