{"id":"eb9e92dedc57cfcd7e60c70f908df827","word":"rotzen","types":[{"type":"verb","lodKey":"ROTZEN1","details":{"auxiliaryVerb":"HUNN","pastParticiples":["gerotzt"],"audio":"rotzen1.m4a"},"meanings":[{"examples":[{"example":"hien huet mir aus puerer Expressegkeet virun d'Féiss gerotzt","usage":"FAM"}],"synonyms":[],"reflexivePronoun":"INTRANSITIF","employsImpersonal":"VRB-EMPL-IMPERS-IMPOSS","translations":[{"language":"ALL","translation":"rotzen","complement":"spucken"},{"language":"FR","translation":"mollarder"},{"language":"PO","translation":"escarrar"},{"language":"EN","translation":"to spit","complement":"to gob"}]},{"examples":[{"example":"deen Drecksak huet eng déck Schnuddel op de Buedem gerotzt","usage":"FAM"}],"synonyms":[],"reflexivePronoun":"TRANSITIF","employsImpersonal":"VRB-EMPL-IMPERS-IMPOSS","translations":[{"language":"ALL","translation":"spucken"},{"language":"FR","translation":"cracher","complement":"rejeter par la bouche"},{"language":"PO","translation":"cuspir","complement":"expelir pela boca"},{"language":"EN","translation":"to spit out"}]}]}]}