{"id":"f548c3f132da709d797ae7d0d45d7cca","word":"Lanthanoid","types":[{"type":"noun","lodKey":"LANTHANOID1","details":{"nounGender":"M","plural":"Lanthanoiden"},"meanings":[{"examples":[{"example":"zum Grupp vun den Lanthanoidgehéieren ënner anerem de Lanthan an den Cer","usage":"ALLG"}],"synonyms":[],"translations":[{"language":"ALL","translation":"Lanthanoid"},{"language":"FR","translation":"lanthanide"},{"language":"PO","translation":"lantanídeo"},{"language":"EN","translation":"lanthanide"}]}]}]}