{"id":"f92b53578d2666e90a0bdab6e6baab9e","word":"méi","types":[{"type":"adverb","lodKey":"MEI1","details":{"audio":"mei1.m4a"},"meanings":[{"examples":[{"example":"ech sinn zwee Joer méi al ewéi mäi Brudder","usage":"ALLG"},{"example":"du bass vläicht staark, mee ech si méi couragéiert!","usage":"ALLG"}],"synonyms":[],"polyLex":"méi ... (ewéi)","translations":[{"language":"ALL","translation":"... (als)"},{"language":"FR","translation":"plus ... (que)"},{"language":"PO","translation":"mais ... (do que)"},{"language":"EN","translation":"... (than)"}]},{"examples":[{"example":"du muss méi no riets zilen, soss trëffs de de Gol ni!","usage":"ALLG"},{"example":"den haitege President setzt sech méi fir säi Veräin an ewéi deen alen","usage":"ALLG"}],"synonyms":[],"translations":[{"language":"ALL","translation":"mehr","complement":"weiter, stärker, eher"},{"language":"FR","translation":"plus","complement":"davantage"},{"language":"PO","translation":"mais","complement":"em maior grau"},{"language":"EN","translation":"more","complement":"to a greater degree"}]},{"examples":[{"example":"schwätz méi haart, ech héieren net méi gutt!","usage":"ALLG"},{"example":"d'Haus gëtt verkaaft, well hien de Prêt net méi kann erëmbezuelen","usage":"ALLG"},{"example":"déi horrend Präisser ka kee sech méi leeschten!","usage":"ALLG"},{"example":"et ass ellen, wann een näischt méi z'iessen huet","usage":"ALLG"}],"synonyms":[],"polyLex":"net méi","translations":[{"language":"ALL","translation":"nicht mehr"},{"language":"FR","translation":"ne ... plus"},{"language":"PO","translation":"já não"},{"language":"EN","translation":"not ... any more"}]},{"examples":[{"example":"well ech nëmme méi mäin Handy benotzen, hunn ech den Haustelefon ofgemellt","usage":"ALLG"}],"synonyms":[],"polyLex":"nëmme méi","translations":[{"language":"ALL","translation":"nur noch","complement":"nichts anderes als"},{"language":"FR","translation":"ne ... plus que","complement":"exclusivement"},{"language":"PO","translation":"(já) só","complement":"exclusivamente"},{"language":"EN","translation":"nothing but","complement":"solely"}]}]}]}