{"id":"fcb12f77ce469c696355ff58bb8c51f3","word":"Comptabilitéit","types":[{"type":"noun","lodKey":"COMPTABILITEIT1","details":{"nounGender":"F","nounCategory":"SUBST"},"meanings":[{"examples":[{"example":"meng Kolleegin ass am Dëschtennisclub fir d' Comptabilitéitzoustänneg","usage":"ALLG"},{"example":"ech schaffen an der Comptabilitéit","usage":"ALLG"}],"synonyms":[],"translations":[{"language":"ALL","translation":"Buchhaltung"},{"language":"FR","translation":"comptabilité"},{"language":"PO","translation":"contabilidade"},{"language":"EN","translation":"accounts"}]}]}]}