{"id":"fcebb59db575dbac0e67f6d0781508bb","word":"Flillek","types":[{"type":"noun","lodKey":"FLILLEK1","details":{"nounGender":"M","nounCategory":"SUBST","plural":"Flilleken","audio":"flillek1.m4a"},"meanings":[{"examples":[{"example":"de Vull huet sech e Flillekgebrach","usage":"ALLG"},{"example":"am Fliger sëtzen ech am léifsten iwwer dem Flillek","usage":"ALLG"}],"synonyms":[],"translations":[{"language":"ALL","translation":"Flügel","complement":"eines Tiers, eines Flugzeugs"},{"language":"FR","translation":"aile","complement":"d'un animal, d'un avion"},{"language":"PO","translation":"asa","complement":"de um animal, de um avião"},{"language":"EN","translation":"wing","complement":"of an animal, of an aircraft"}]}]}]}