{"id":"fd29946e12f7cd2d9385d3da55e69f10","word":"gläichgülteg","types":[{"type":"adjective","lodKey":"GLAICHGULTEG1","details":{"audio":"glaichgulteg1.m4a"},"meanings":[{"examples":[{"example":"d'Situatioun am Krisegebitt kann een net gläichgülteg loossen","usage":"ALLG"}],"synonyms":[],"translations":[{"language":"ALL","translation":"gleichgültig","complement":"teilnahmslos"},{"language":"FR","translation":"indifférent","complement":"insensible, insoucieux"},{"language":"PO","translation":"indiferente","complement":"insensível, indolente"},{"language":"EN","translation":"indifferent"}]},{"examples":[{"example":"d'Aarmut an der Welt sollt kengem gläichgülteg sinn","usage":"ALLG"}],"synonyms":[],"polyLex":"gläichgülteg sinn","translations":[{"language":"ALL","translation":"gleichgültig sein"},{"language":"FR","translation":"être indifférent à"},{"language":"PO","translation":"ser indiferente a","complement":"não interessar a"},{"language":"EN","translation":"to be all the same"}]}]}]}